[
  {
    "text": "No one can make you feel inferior without your consent.",
    "author": "Eleanor Roosevelt"
  },
  {
    "text": "If you tell the truth, you don't have to remember anything.",
    "author": "Mark Twain"
  },
  {
    "text": "In three words I can sum up everything I've learned about life: it goes on.",
    "author": "Robert Frost"
  },
  {
    "text": "It is better to remain silent at the risk of being thought a fool, than to talk and remove all doubt of it.",
    "author": "Maurice Switzer"
  },
  {
    "text": "The fool doth think he is wise, but the wise man knows himself to be a fool.",
    "author": "William Shakespeare"
  },
  {
    "text": "No",
    "author": "Rosa Parks"
  },
  {
    "text": "But how will I eat cake if my head is over there, and my hands are over here?",
    "author": "Marie Antoinette"
  },
  {
    "text": "The trouble with having an open mind, of course, is that people will insist on coming along and trying to put things in it.",
    "author": "Terry Pratchett"
  },
  {
    "text": "text",
    "author": "author"
  },
  {
    "text": "text",
    "author": "author"
  },
  {
    "text": "text",
    "author": "author"
  },
  {
    "text": "text",
    "author": "author"
  },
  {
    "text": "text",
    "author": "author"
  }
]
